README.rst
setup.cfg
setup.py
arybo/__init__.py
arybo.egg-info/PKG-INFO
arybo.egg-info/SOURCES.txt
arybo.egg-info/dependency_links.txt
arybo.egg-info/requires.txt
arybo.egg-info/top_level.txt
arybo/lib/__init__.py
arybo/lib/bool_solver.py
arybo/lib/exprs_asm.py
arybo/lib/exprs_passes.py
arybo/lib/mba_exprs.py
arybo/lib/mba_if.py
arybo/lib/mba_impl_petanque.py
arybo/lib/mba_impl_sympy.py
arybo/lib/tester.py
arybo/tools/__init__.py
arybo/tools/identify.py
arybo/tools/petanque.py
arybo/tools/triton_.py
bin/iarybo