Metadata-Version: 1.1
Name: arybo
Version: 1.0.0
Summary: Manipulation, canonicalization and identification of mixed boolean-arithmetic symbolic expressions
Home-page: https://github.com/quarkslab/arybo
Author: Adrien Guinet
Author-email: aguinet@quarkslab.com
License: BSD
Download-URL: https://github.com/quarkslab/arybo/releases
Keywords: symbolic computation canonicalization boolean-arithmetic expressions
Platform: UNKNOWN
Classifier: Development Status :: 4 - Beta
Classifier: Intended Audience :: Science/Research
Classifier: Intended Audience :: Developers
Classifier: Topic :: Software Development :: Build Tools
Classifier: Topic :: Security
Classifier: Topic :: Scientific/Engineering
Classifier: License :: OSI Approved :: BSD License
Classifier: Programming Language :: Python :: 3
Classifier: Programming Language :: Python :: 3.2
Classifier: Programming Language :: Python :: 3.3
Classifier: Programming Language :: Python :: 3.4
Classifier: Programming Language :: Python :: 3.5
